[
  {
    "termino": "REST",
    "definicion": "Estilo de arquitectura para servicios web basado en recursos.",
    "fuente": "RESTful Web Services - Richardson & Ruby"
  },
  {
    "termino": "SOAP",
    "definicion": "Protocolo basado en XML para intercambio estructurado de informaci칩n.",
    "fuente": "SOAP 1.2 Specification"
  },
  {
    "termino": "XML",
    "definicion": "XML es un lenguaje de marcado para estructurar e intercambiar datos.",
    "fuente": "XML 1.0 Specification"
  },
  {
    "termino": "WSDL",
    "definicion": "WSDL es un lenguaje en XML que describe servicios web y c칩mo acceder a ellos.",
    "fuente": "WSDL 1.1 Specification"
  },
  {
    "termino": "UDDI",
    "definicion": "UDDI es un est치ndar para la publicaci칩n y descubrimiento de servicios web.",
    "fuente": "UDDI specification"
  }
]
